LICENSE
code_loader/__init__.py
code_loader/contract/__init__.py
code_loader/contract/datasetclasses.py
code_loader/contract/enums.py
code_loader/contract/exceptions.py
code_loader/contract/mapping.py
code_loader/contract/responsedataclasses.py
code_loader/contract/visualizer_classes.py
code_loader/default_losses.py
code_loader/default_metrics.py
code_loader/experiment_api/__init__.py
code_loader/experiment_api/api.py
code_loader/experiment_api/cli_config_utils.py
code_loader/experiment_api/client.py
code_loader/experiment_api/epoch.py
code_loader/experiment_api/experiment.py
code_loader/experiment_api/experiment_context.py
code_loader/experiment_api/types.py
code_loader/experiment_api/utils.py
code_loader/experiment_api/workingspace_config_utils.py
code_loader/inner_leap_binder/__init__.py
code_loader/inner_leap_binder/leapbinder.py
code_loader/inner_leap_binder/leapbinder_decorators.py
code_loader/leaploader.py
code_loader/leaploaderbase.py
code_loader/mixpanel_tracker.py
code_loader/plot_functions/__init__.py
code_loader/plot_functions/plot_functions.py
code_loader/plot_functions/visualize.py
code_loader/utils.py
code_loader/visualizers/__init__.py
code_loader/visualizers/default_visualizers.py
code_loader-1.0.152.dist-info/LICENSE
code_loader-1.0.152.dist-info/METADATA
code_loader-1.0.152.dist-info/WHEEL
code_loader-1.0.152.dist-info/RECORD
